cel_python/__init__.py
cel_python/built_in_functions.py~
cel_python/cel_python.py
cel_python/cli.py
cel_python/context.py
cel_python/context.py~
cel_python/error_collector.py
cel_python/error_collector.py~
cel_python/evaluator.py~
cel_python/interpreter.py
cel_python/interpreter.py~
cel_python/runtime.py
cel_python/runtime.py~
cel_python/runtine.py~
cel_python/type_checker.py
cel_python/type_checker.py~
cel_python/parser/#CELParser.py#
cel_python/parser/CEL.interp
cel_python/parser/CEL.tokens
cel_python/parser/CELLexer.interp
cel_python/parser/CELLexer.py
cel_python/parser/CELLexer.tokens
cel_python/parser/CELListener.py
cel_python/parser/CELParser.py
cel_python/parser/CELVisitor.py
cel_python/parser/__init__.py
gresb_cel_python-0.0.3.dist-info/LICENSE
gresb_cel_python-0.0.3.dist-info/METADATA
gresb_cel_python-0.0.3.dist-info/WHEEL
gresb_cel_python-0.0.3.dist-info/top_level.txt
gresb_cel_python-0.0.3.dist-info/RECORD
